LICENSE
MANIFEST.in
README.md
install.json
package.json
requirements.txt
setup.cfg
setup.py
solas_widget.egg-info/PKG-INFO
solas_widget.egg-info/SOURCES.txt
solas_widget.egg-info/dependency_links.txt
solas_widget.egg-info/not-zip-safe
solas_widget.egg-info/requires.txt
solas_widget.egg-info/top_level.txt
solaswidget/__init__.py
solaswidget/_frontend.py
solaswidget/_version.py
solaswidget/widget.py
solaswidget/labextension/package.json
solaswidget/labextension/static/367.83e4d8e5c8012d1b1f0e.js
solaswidget/labextension/static/430.1ac99c3ff59bee29f6fc.js
solaswidget/labextension/static/430.1ac99c3ff59bee29f6fc.js.LICENSE.txt
solaswidget/labextension/static/480.7d24a76a8fd9d463031b.js
solaswidget/labextension/static/500.915cc014569667c58489.js
solaswidget/labextension/static/501.8a4fd550b24dea212cbb.js
solaswidget/labextension/static/568.02c7a14732f6435512be.js
solaswidget/labextension/static/713.87b01bbf923a354c9364.js
solaswidget/labextension/static/755.0e5b33cc0b3e51a40e88.js
solaswidget/labextension/static/755.0e5b33cc0b3e51a40e88.js.LICENSE.txt
solaswidget/labextension/static/776.31191654d2db7eba4e7e.js
solaswidget/labextension/static/8.2226a4715d8349780581.js
solaswidget/labextension/static/8.2226a4715d8349780581.js.LICENSE.txt
solaswidget/labextension/static/823.8cb45879b82c4eeb4f91.js
solaswidget/labextension/static/839.be71e4e30c90ccdeacb7.js
solaswidget/labextension/static/866.2493722bc2e924beccef.js
solaswidget/labextension/static/921.80cdee21b8dcebfafad4.js
solaswidget/labextension/static/921.80cdee21b8dcebfafad4.js.LICENSE.txt
solaswidget/labextension/static/989.79bec672eac148b96bb0.js
solaswidget/labextension/static/remoteEntry.0aea318e88f590026777.js
solaswidget/labextension/static/style.js
solaswidget/labextension/static/third-party-licenses.json
solaswidget/nbextension/__init__.py
solaswidget/nbextension/package.json
solaswidget/nbextension/static/extension.js
solaswidget/nbextension/static/index.js
solaswidget/nbextension/static/index.js.map